score.perf-0.0.5-py3.7-nspkg.pth
score/perf/__init__.py
score/perf/_init.py
score/perf/stopwatch.py
score.perf-0.0.5.dist-info/COPYING.LESSER.txt
score.perf-0.0.5.dist-info/METADATA
score.perf-0.0.5.dist-info/WHEEL
score.perf-0.0.5.dist-info/namespace_packages.txt
score.perf-0.0.5.dist-info/top_level.txt
score.perf-0.0.5.dist-info/RECORD
